bioforklift/__init__.py
bioforklift/alerting/__init__.py
bioforklift/alerting/sentry.py
bioforklift/alerting/slack.py
bioforklift/bigquery/__init__.py
bioforklift/bigquery/bigquery.py
bioforklift/bigquery/client.py
bioforklift/bigquery/config_operations.py
bioforklift/bigquery/sample_operations.py
bioforklift/data_processing/__init__.py
bioforklift/data_processing/config_processor.py
bioforklift/data_processing/sample_processor.py
bioforklift/data_processing/schema_converter.py
bioforklift/data_processing/schema_models.py
bioforklift/data_processing/utils.py
bioforklift/file_transfers/__init__.py
bioforklift/file_transfers/gcs_transfer.py
bioforklift/forklift_logging.py
bioforklift/terra/__init__.py
bioforklift/terra/client.py
bioforklift/terra/exceptions.py
bioforklift/terra/models.py
bioforklift/terra/terra.py
bioforklift/terra/terra_entities.py
bioforklift/terra/terra_merge.py
bioforklift/terra/terra_submissions.py
bioforklift/terra/utils.py
bioforklift/terra2bq/__init__.py
bioforklift/terra2bq/config_builder.py
bioforklift/terra2bq/models.py
bioforklift/terra2bq/terra2bq.py
bioforklift-0.3.4.dist-info/LICENSE
bioforklift-0.3.4.dist-info/METADATA
bioforklift-0.3.4.dist-info/WHEEL
bioforklift-0.3.4.dist-info/RECORD
