Metadata-Version: 2.1
Name: bioforklift
Version: 0.3.4
Summary: Package for handling bioinformatics data automations between data sources
License: GPL-3.0
Keywords: terra,bigquery,bioinformatics,data-integration
Author: Michal-Babins
Author-email: michal.babinski@theiagen.com
Requires-Python: >=3.10,<4.0
Classifier: License :: OSI Approved :: GNU General Public License v3 (GPLv3)
Classifier: Programming Language :: Python :: 3
Classifier: Programming Language :: Python :: 3.10
Classifier: Programming Language :: Python :: 3.11
Classifier: Programming Language :: Python :: 3.12
Requires-Dist: google (>=3.0.0,<4.0.0)
Requires-Dist: google-api-core (>=2.24.1,<3.0.0)
Requires-Dist: google-api-python-client (>=2.160.0,<3.0.0)
Requires-Dist: google-cloud-bigquery (>=3.29.0,<4.0.0)
Requires-Dist: google-cloud-storage (>=3.1.0,<4.0.0)
Requires-Dist: mkdocs (>=1.6.1,<2.0.0)
Requires-Dist: mkdocs-material (>=9.6.9,<10.0.0)
Requires-Dist: pandas (>=2.2.3,<3.0.0)
Requires-Dist: pandas-gbq (>=0.28.0,<0.29.0)
Requires-Dist: pyarrow (>=19.0.1,<20.0.0)
Requires-Dist: pydantic (>=2.10.6,<3.0.0)
Requires-Dist: pytest-mock (>=3.14.0,<4.0.0)
Requires-Dist: pyyaml (>=6.0.2,<7.0.0)
Requires-Dist: requests (>=2.32.3,<3.0.0)
Requires-Dist: sentry-sdk (>=2.33.2,<3.0.0)
Requires-Dist: sqlalchemy (>=2.0.41,<3.0.0)
